MANIFEST.in
README.md
setup.py
kittens/__init__.py
kittens/__main__.py
kittens.egg-info/PKG-INFO
kittens.egg-info/SOURCES.txt
kittens.egg-info/dependency_links.txt
kittens.egg-info/top_level.txt