Metadata-Version: 1.0
Name: kittens
Version: 0.1.2
Summary: A means of sending friendly images of kittens to a target.
Home-page: http://pypi.python.org/pypi/kittens/
Author: Samuel "mansam" Lucidi
Author-email: mansam@csh.rit.edu
License: LICENSE
Platform: UNKNOWN
